docugami_langchain/__init__.py
docugami_langchain/agents/__init__.py
docugami_langchain/agents/base.py
docugami_langchain/agents/models.py
docugami_langchain/agents/re_act_agent.py
docugami_langchain/agents/tool_router_agent.py
docugami_langchain/base_runnable.py
docugami_langchain/chains/__init__.py
docugami_langchain/chains/answer_chain.py
docugami_langchain/chains/base.py
docugami_langchain/chains/chunks/__init__.py
docugami_langchain/chains/chunks/elaborate_chunk_chain.py
docugami_langchain/chains/chunks/summarize_chunk_chain.py
docugami_langchain/chains/documents/__init__.py
docugami_langchain/chains/documents/describe_document_set_chain.py
docugami_langchain/chains/documents/summarize_document_chain.py
docugami_langchain/chains/querying/__init__.py
docugami_langchain/chains/querying/docugami_explained_sql_query_chain.py
docugami_langchain/chains/querying/models.py
docugami_langchain/chains/querying/sql_fixup_chain.py
docugami_langchain/chains/querying/sql_query_explainer_chain.py
docugami_langchain/chains/querying/sql_result_chain.py
docugami_langchain/chains/querying/sql_result_explainer_chain.py
docugami_langchain/chains/rag/__init__.py
docugami_langchain/chains/rag/models.py
docugami_langchain/chains/rag/retrieval_grader_chain.py
docugami_langchain/chains/rag/simple_rag_chain.py
docugami_langchain/chains/rag/standalone_question_chain.py
docugami_langchain/chains/rag/suggested_questions_chain.py
docugami_langchain/chains/rag/suggested_report_chain.py
docugami_langchain/chains/rag/tool_final_answer_chain.py
docugami_langchain/chains/rag/tool_output_grader_chain.py
docugami_langchain/chains/types/__init__.py
docugami_langchain/chains/types/address_parse_chain.py
docugami_langchain/chains/types/common.py
docugami_langchain/chains/types/data_type_detection_chain.py
docugami_langchain/chains/types/date_add_chain.py
docugami_langchain/chains/types/date_parse_chain.py
docugami_langchain/chains/types/float_parse_chain.py
docugami_langchain-0.0.22.dist-info/LICENSE
docugami_langchain-0.0.22.dist-info/METADATA
docugami_langchain-0.0.22.dist-info/WHEEL
docugami_langchain-0.0.22.dist-info/RECORD
