Metadata-Version: 2.1
Name: docugami-langchain
Version: 0.0.22
Summary: Docugami partner package for LangChain
Home-page: https://github.com/docugami/docugami-langchain
License: MIT
Requires-Python: >=3.9,<4.0
Classifier: License :: OSI Approved :: MIT License
Classifier: Programming Language :: Python :: 3
Classifier: Programming Language :: Python :: 3.9
Classifier: Programming Language :: Python :: 3.10
Classifier: Programming Language :: Python :: 3.11
Classifier: Programming Language :: Python :: 3.12
Requires-Dist: dgml-utils (>=0.3.3)
Requires-Dist: langchain-community (>=0.2.0)
Requires-Dist: langchain-core (>=0.2.1)
Requires-Dist: langgraph (>=0.0.55)
Requires-Dist: openpyxl (>=3.1.2)
Requires-Dist: pandas
Requires-Dist: python-dateutil (>=2.9.0)
Requires-Dist: pyyaml (>=6.0.1)
Requires-Dist: sqlglot (>=24.0.0)
Requires-Dist: tabulate (>=0.9.0)
Requires-Dist: wordtodigits (>=1.0.2)
Project-URL: Repository, https://github.com/docugami/docugami-langchain
Project-URL: Source Code, https://github.com/docugami/docugami-langchain/tree/master
